setup.py
Yusir_app/__init__.py
Yusir_app.egg-info/PKG-INFO
Yusir_app.egg-info/SOURCES.txt
Yusir_app.egg-info/dependency_links.txt
Yusir_app.egg-info/top_level.txt