Metadata-Version: 2.1
Name: Yusir_app
Version: 0.0.2
Summary: some function for rpa_application 
Author: Yu.sir
Author-email: linxing_1@163.com
